{
    "progetti": [
        
        {
            "nome": "Pokenav (work in progress)",
            "tech": [
                {
                    "title": "Dart",
                    "color": "#0175C2"
                },
                {
                    "title": "Flutter",
                    "color": "#02569B"
                },
                {
                    "title": "Stream based API",
                    "color": "#FF6B35"
                },
                {
                    "title": "Auto Caching",
                    "color": "#8E44AD"
                }
            ],
            "url": "https://github.com/Channilol/Pokenav",
            "image_url": ""
        },
        {
            "nome": "PokeCollector",
            "tech": [
                {
                    "title": "React.js",
                    "color": "#3996b8"
                },
                {
                    "title": "C#",
                    "color": "#178600"
                },
                {
                    "title": ".NET",
                    "color": "#512bd4"
                },
                {
                    "title": "SQL",
                    "color": "#e38c00"
                }
            ],
            "url": "https://github.com/Channilol/PokeCollectorFRONTEND",
            "image_file": "PokeCollector.png"
        },
        {
            "nome": "Weather App",
            "tech": [
               {
                    "title": "React.js",
                    "color": "#3996b8"
                }
            ],
            "url": "https://github.com/Channilol/WeatherWebAppReact",
            "image_url": "WeatherApp.png"
        }
    ]
}